qlsdk/__init__.py
qlsdk/ar4/__init__.py
qlsdk/ar4m/__init__.py
qlsdk/core/__init__.py
qlsdk/core/device.py
qlsdk/core/exception.py
qlsdk/core/local.py
qlsdk/core/utils.py
qlsdk/core/crc/__init__.py
qlsdk/core/crc/crctools.py
qlsdk/core/entity/__init__.py
qlsdk/core/filter/__init__.py
qlsdk/core/filter/norch.py
qlsdk/core/message/__init__.py
qlsdk/core/message/command.py
qlsdk/core/message/tcp.py
qlsdk/core/message/udp.py
qlsdk/core/network/__init__.py
qlsdk/core/network/monitor.py
qlsdk/entity/__init__.py
qlsdk/entity/message.py
qlsdk/entity/signal.py
qlsdk/interface/__init__.py
qlsdk/interface/analyzer.py
qlsdk/interface/collector.py
qlsdk/interface/device.py
qlsdk/interface/parser.py
qlsdk/interface/stimulator.py
qlsdk/interface/store.py
qlsdk/persist/__init__.py
qlsdk/persist/ars_edf.py
qlsdk/persist/edf.py
qlsdk/persist/rsc_edf.py
qlsdk/persist/stream.py
qlsdk/rsc/__init__.py
qlsdk/rsc/device_manager.py
qlsdk/rsc/discover.py
qlsdk/rsc/eegion.py
qlsdk/rsc/entity.py
qlsdk/rsc/paradigm.py
qlsdk/rsc/proxy.py
qlsdk/rsc/command/__init__.py
qlsdk/rsc/command/message.py
qlsdk/rsc/device/__init__.py
qlsdk/rsc/device/arskindling.py
qlsdk/rsc/device/base.py
qlsdk/rsc/device/c16_rs.py
qlsdk/rsc/device/c256_rs.py
qlsdk/rsc/device/c64_rs.py
qlsdk/rsc/device/c64s1.py
qlsdk/rsc/device/device_factory.py
qlsdk/rsc/interface/__init__.py
qlsdk/rsc/interface/command.py
qlsdk/rsc/interface/device.py
qlsdk/rsc/interface/handler.py
qlsdk/rsc/interface/parser.py
qlsdk/rsc/manager/__init__.py
qlsdk/rsc/manager/container.py
qlsdk/rsc/manager/search.py
qlsdk/rsc/network/__init__.py
qlsdk/rsc/network/discover.py
qlsdk/rsc/parser/__init__.py
qlsdk/rsc/parser/base-new.py
qlsdk/rsc/parser/base.py
qlsdk/rsc/parser/rsc.py
qlsdk/sdk/__init__.py
qlsdk/sdk/ar4sdk.py
qlsdk/sdk/hub.py
qlsdk/sdk/libs/libAr4SDK.dll
qlsdk/sdk/libs/libwinpthread-1.dll
qlsdk/x8/__init__.py
qlsdk/x8m/__init__.py
qlsdk2-0.6.0.dist-info/METADATA
qlsdk2-0.6.0.dist-info/WHEEL
qlsdk2-0.6.0.dist-info/top_level.txt
qlsdk2-0.6.0.dist-info/RECORD
