Metadata-Version: 2.1
Name: qlsdk2
Version: 0.6.0
Summary: SDK for quanlan device
Home-page: https://github.com/hehuajun/qlsdk
Author: hehuajun
Author-email: hehuajun@eegion.com
Classifier: Programming Language :: Python :: 3
Classifier: License :: OSI Approved :: MIT License
Classifier: Operating System :: Microsoft :: Windows :: Windows 10
Requires-Python: >=3.9
Requires-Dist: loguru >=0.6.0
Requires-Dist: numpy >=1.23.5
Requires-Dist: bitarray >=1.5.3
Provides-Extra: dev
Requires-Dist: pytest >=6.0 ; extra == 'dev'
Requires-Dist: twine >=3.0 ; extra == 'dev'
